LICENSE
README.md
setup.cfg
setup.py
vexpr/__init__.py
vexpr/core.py
vexpr/vectorization.py
vexpr.egg-info/PKG-INFO
vexpr.egg-info/SOURCES.txt
vexpr.egg-info/dependency_links.txt
vexpr.egg-info/top_level.txt
vexpr/custom/__init__.py
vexpr/custom/numpy/__init__.py
vexpr/custom/numpy/primitives.py
vexpr/custom/numpy/register_eval.py
vexpr/custom/scipy/__init__.py
vexpr/custom/scipy/primitives.py
vexpr/custom/scipy/register_eval.py
vexpr/custom/torch/__init__.py
vexpr/custom/torch/primitives.py
vexpr/custom/torch/register_eval.py
vexpr/custom/torch/register_pushthrough.py
vexpr/custom/torch/register_vectorize.py
vexpr/custom/torch/utils.py
vexpr/numpy/__init__.py
vexpr/numpy/primitives.py
vexpr/numpy/register_eval.py
vexpr/numpy/register_pushthrough.py
vexpr/numpy/register_vectorize.py
vexpr/scipy/__init__.py
vexpr/scipy/spatial/__init__.py
vexpr/scipy/spatial/distance.py
vexpr/scipy/spatial/primitives.py
vexpr/scipy/spatial/register_eval.py
vexpr/scipy/spatial/register_pushthrough.py
vexpr/torch/__init__.py
vexpr/torch/primitives.py
vexpr/torch/register_eval.py
vexpr/torch/register_pushthrough.py
vexpr/torch/register_vectorize.py
vexpr/torch/utils.py